mercury_sync/__init__.py
mercury_sync/connection/__init__.py
mercury_sync/connection/addresses/__init__.py
mercury_sync/connection/addresses/subnet_range.py
mercury_sync/connection/base/__init__.py
mercury_sync/connection/base/connection_type.py
mercury_sync/connection/tcp/__init__.py
mercury_sync/connection/tcp/mercury_sync_http_connection.py
mercury_sync/connection/tcp/mercury_sync_tcp_connection.py
mercury_sync/connection/tcp/protocols/__init__.py
mercury_sync/connection/tcp/protocols/mercury_sync_tcp_client_protocol.py
mercury_sync/connection/tcp/protocols/mercury_sync_tcp_server_protocol.py
mercury_sync/connection/udp/__init__.py
mercury_sync/connection/udp/mercury_sync_udp_connection.py
mercury_sync/connection/udp/mercury_sync_udp_multicast_connection.py
mercury_sync/connection/udp/protocols/__init__.py
mercury_sync/connection/udp/protocols/mercury_sync_udp_protocol.py
mercury_sync/discovery/__init__.py
mercury_sync/discovery/dns/__init__.py
mercury_sync/discovery/dns/registrar.py
mercury_sync/discovery/dns/core/__init__.py
mercury_sync/discovery/dns/core/cache/__init__.py
mercury_sync/discovery/dns/core/cache/cache_node.py
mercury_sync/discovery/dns/core/cache/cache_value.py
mercury_sync/discovery/dns/core/config/__init__.py
mercury_sync/discovery/dns/core/config/nt.py
mercury_sync/discovery/dns/core/config/posix.py
mercury_sync/discovery/dns/core/config/root.py
mercury_sync/discovery/dns/core/exceptions/__init__.py
mercury_sync/discovery/dns/core/exceptions/dns_error.py
mercury_sync/discovery/dns/core/exceptions/invalid_service_url_error.py
mercury_sync/discovery/dns/core/exceptions/utils/__init__.py
mercury_sync/discovery/dns/core/exceptions/utils/get_bits.py
mercury_sync/discovery/dns/core/nameservers/__init__.py
mercury_sync/discovery/dns/core/nameservers/exceptions.py
mercury_sync/discovery/dns/core/nameservers/nameserver.py
mercury_sync/discovery/dns/core/random/__init__.py
mercury_sync/discovery/dns/core/random/random_id_generator.py
mercury_sync-0.4.2.dist-info/LICENSE
mercury_sync-0.4.2.dist-info/METADATA
mercury_sync-0.4.2.dist-info/WHEEL
mercury_sync-0.4.2.dist-info/top_level.txt
mercury_sync-0.4.2.dist-info/RECORD
