Metadata-Version: 2.1
Name: mercury-sync
Version: 0.4.2
Summary: A pure-Python, asyncio based library for authoring distributed systems
Home-page: https://github.com/scorbettUM/mercury-sync
Author: Sean Corbett
Author-email: sean.corbett@umontana.edu
Keywords: pypi,python,distributed systems,swim,serf,distributed
Classifier: Programming Language :: Python :: 3.8
Classifier: Programming Language :: Python :: 3.9
Classifier: Programming Language :: Python :: 3.10
Classifier: Programming Language :: Python :: 3.11
Classifier: License :: OSI Approved :: MIT License
Classifier: Operating System :: OS Independent
Requires-Python: >=3.10
License-File: LICENSE
Requires-Dist: pydantic
Requires-Dist: python3-dtls
Requires-Dist: zstandard
Requires-Dist: cryptography
Requires-Dist: python-dotenv
